otsrdflib/__init__.py
otsrdflib/ots.py
otsrdflib-0.5.0.dist-info/DESCRIPTION.rst
otsrdflib-0.5.0.dist-info/METADATA
otsrdflib-0.5.0.dist-info/RECORD
otsrdflib-0.5.0.dist-info/WHEEL
otsrdflib-0.5.0.dist-info/metadata.json
otsrdflib-0.5.0.dist-info/pbr.json
otsrdflib-0.5.0.dist-info/top_level.txt
otsrdflib-0.5.0.dist-info/zip-safe
