Metadata-Version: 1.1
Name: otsrdflib
Version: 0.5.0
Summary: Ordered Turtle Serializer for rdflib
Home-page: https://github.com/scriptotek/otsrdflib
Author: Dan Michael O. Heggø
Author-email: danmichaelo@gmail.com
License: MIT
Keywords: rdflib turtle serializer
Platform: UNKNOWN
Classifier: Programming Language :: Python
Classifier: Programming Language :: Python :: 2.7
Classifier: Programming Language :: Python :: 3.4
Classifier: Programming Language :: Python :: 3.5
Classifier: Programming Language :: Python :: 3.6
